specutils/__init__.py
specutils/conftest.py
specutils/version.py
specutils/analysis/__init__.py
specutils/analysis/correlation.py
specutils/analysis/flux.py
specutils/analysis/location.py
specutils/analysis/moment.py
specutils/analysis/template_comparison.py
specutils/analysis/uncertainty.py
specutils/analysis/utils.py
specutils/analysis/width.py
specutils/fitting/__init__.py
specutils/fitting/continuum.py
specutils/fitting/fitmodels.py
specutils/io/__init__.py
specutils/io/_list_of_loaders.py
specutils/io/parsing_utils.py
specutils/io/registers.py
specutils/io/asdf/__init__.py
specutils/io/asdf/converters.py
specutils/io/asdf/extension.py
specutils/io/asdf/manifests/specutils-1.0.0.yaml
specutils/io/asdf/manifests/specutils-1.1.0.yaml
specutils/io/asdf/schemas/spectrum-1.0.0.yaml
specutils/io/asdf/schemas/spectrum1d-1.0.0.yaml
specutils/io/asdf/schemas/spectrum_list-1.0.0.yaml
specutils/io/asdf/tests/__init__.py
specutils/io/asdf/tests/helpers.py
specutils/io/asdf/tests/test_spectra.py
specutils/io/default_loaders/__init__.py
specutils/io/default_loaders/aaomega_2df.py
specutils/io/default_loaders/apogee.py
specutils/io/default_loaders/ascii.py
specutils/io/default_loaders/dc_common.py
specutils/io/default_loaders/desi.py
specutils/io/default_loaders/galah.py
specutils/io/default_loaders/gama.py
specutils/io/default_loaders/generic_cube.py
specutils/io/default_loaders/generic_ecsv_reader.py
specutils/io/default_loaders/hst_cos.py
specutils/io/default_loaders/hst_stis.py
specutils/io/default_loaders/jwst_reader.py
specutils/io/default_loaders/manga.py
specutils/io/default_loaders/muscles_sed.py
specutils/io/default_loaders/ozdes.py
specutils/io/default_loaders/sami.py
specutils/io/default_loaders/sdss.py
specutils/io/default_loaders/sdss_v.py
specutils/io/default_loaders/sixdfgs_reader.py
specutils/io/default_loaders/subaru_pfs_spec.py
specutils/io/default_loaders/tabular_fits.py
specutils/io/default_loaders/twodfgrs_reader.py
specutils-2.2.0.dist-info/licenses/licenses/LICENSE.rst
specutils-2.2.0.dist-info/METADATA
specutils-2.2.0.dist-info/WHEEL
specutils-2.2.0.dist-info/entry_points.txt
specutils-2.2.0.dist-info/top_level.txt
specutils-2.2.0.dist-info/RECORD
