Metadata-Version: 2.4
Name: specutils
Version: 2.2.0
Summary: Package for spectroscopic astronomical data
Author: Specutils Developers
Author-email: coordinators@astropy.org
License: BSD 3-Clause
Project-URL: Source, https://github.com/astropy/specutils
Project-URL: Documentation, https://specutils.readthedocs.io
Classifier: Intended Audience :: Science/Research
Classifier: License :: OSI Approved :: BSD License
Classifier: Operating System :: OS Independent
Classifier: Programming Language :: Python
Classifier: Programming Language :: Python :: 3
Classifier: Topic :: Scientific/Engineering :: Astronomy
Classifier: Topic :: Software Development :: Libraries
Requires-Python: >=3.11
License-File: licenses/LICENSE.rst
Requires-Dist: numpy>=1.24
Requires-Dist: scipy>=1.14
Requires-Dist: astropy>=7.0
Requires-Dist: gwcs>=0.22
Requires-Dist: asdf-astropy>=0.5
Requires-Dist: asdf>=3.3.0
Requires-Dist: ndcube>=2.0
Provides-Extra: test
Requires-Dist: pytest-asdf-plugin; extra == "test"
Requires-Dist: pytest-astropy; extra == "test"
Requires-Dist: tox; extra == "test"
Requires-Dist: matplotlib; extra == "test"
Requires-Dist: spectral-cube; extra == "test"
Provides-Extra: jwst
Requires-Dist: stdatamodels>=1.1.0; extra == "jwst"
Provides-Extra: docs
Requires-Dist: sphinx-astropy; extra == "docs"
Requires-Dist: matplotlib; extra == "docs"
Requires-Dist: graphviz; extra == "docs"
Dynamic: license-file
